qprof_myqlm/NamedRoutine.py
qprof_myqlm/RoutineWrapper.py
qprof_myqlm/__init__.py
qprof_myqlm/_interfaces.py
qprof_myqlm/name_routines.py
qprof_myqlm/supports_routine_test.py
qprof_qat/NamedRoutine.py
qprof_qat/RoutineWrapper.py
qprof_qat/__init__.py
qprof_qat/_interfaces.py
qprof_qat/name_routines.py
qprof_qat/supports_routine_test.py
qprof_myqlm-1.0.1.dist-info/LICENSE
qprof_myqlm-1.0.1.dist-info/METADATA
qprof_myqlm-1.0.1.dist-info/WHEEL
qprof_myqlm-1.0.1.dist-info/top_level.txt
qprof_myqlm-1.0.1.dist-info/RECORD
